MANIFEST.in
requirements.txt
setup.py
xossynchronizer/VERSION
xossynchronizer/__init__.py
xossynchronizer/apiaccessor.py
xossynchronizer/backend.py
xossynchronizer/backend_modelpolicy.py
xossynchronizer/dependency_walker_new.py
xossynchronizer/event_engine.py
xossynchronizer/event_loop.py
xossynchronizer/exceptions.py
xossynchronizer/loadmodels.py
xossynchronizer/mock_modelaccessor_build.py
xossynchronizer/model_policy_loop.py
xossynchronizer/modelaccessor.py
xossynchronizer/pull_step_engine.py
xossynchronizer/synchronizer.py
xossynchronizer.egg-info/PKG-INFO
xossynchronizer.egg-info/SOURCES.txt
xossynchronizer.egg-info/dependency_links.txt
xossynchronizer.egg-info/requires.txt
xossynchronizer.egg-info/top_level.txt
xossynchronizer/event_steps/__init__.py
xossynchronizer/event_steps/eventstep.py
xossynchronizer/model_policies/__init__.py
xossynchronizer/model_policies/policy.py
xossynchronizer/pull_steps/__init__.py
xossynchronizer/pull_steps/pullstep.py
xossynchronizer/steps/__init__.py
xossynchronizer/steps/syncstep.py