Metadata-Version: 1.1
Name: xossynchronizer
Version: 3.1.0
Summary: XOS Synchronizer Framework
Home-page: UNKNOWN
Author: Scott Baker
Author-email: scottb@opennetworking.org
License: Apache v2
Platform: UNKNOWN
Classifier: License :: OSI Approved :: Apache Software License
